causate/__init__.py
causate/core.py
causate/model_scripts.py
causate/utils.py
causate-0.1.1.dist-info/LICENSE
causate-0.1.1.dist-info/METADATA
causate-0.1.1.dist-info/WHEEL
causate-0.1.1.dist-info/top_level.txt
causate-0.1.1.dist-info/RECORD
